logistock/__init__.py
logistock/api.py
logistock/configuration.py
logistock/gestionnaire.py
logistock/moteur_mcts.py
logistock-0.1.3.dist-info/METADATA
logistock-0.1.3.dist-info/WHEEL
logistock-0.1.3.dist-info/top_level.txt
logistock-0.1.3.dist-info/RECORD
