Metadata-Version: 2.4
Name: logistock
Version: 0.1.3
Summary: Simulation de la dynamique d'un stock de marchandise empilees
Author-email: Groupe 12 <ninadefo00@gmail.com>
Requires-Python: >=3.8
